{
  "cookies": [
    {
      "name": "OTZ",
      "value": "8034550_48_52_123900_48_436380",
      "domain": "accounts.google.com",
      "path": "/",
      "expires": 1746969012,
      "httpOnly": false,
      "secure": true,
      "sameSite": "Lax"
    },
    {
      "name": "SID",
      "value": "g.a000vwhL4N3uIaXr_vZWHim6u55wOulT-VdaUqjxM1YX88tK2JJt81RO2Ut6xhpYNcdAe_rw4wACgYKAaQSARESFQHGX2MiHf8vzqgzesHILBxz3k7mWxoVAUF8yKrS9GBzogQukA0U9LIXf0hL0076",
      "domain": ".google.com",
      "path": "/",
      "expires": 1778937017.511033,
      "httpOnly": false,
      "secure": false,
      "sameSite": "Lax"
    },
    {
      "name": "__Secure-1PSID",
      "value": "g.a000vwhL4N3uIaXr_vZWHim6u55wOulT-VdaUqjxM1YX88tK2JJtsLsDACqkvvs4EYnI9Q2S3AACgYKASgSARESFQHGX2Mi3mTF1WJbb-6jaVsJfq5QfRoVAUF8yKqIoUFFV7AI08eQyGheu4JR0076",
      "domain": ".google.com",
      "path": "/",
      "expires": 1778937017.511085,
      "httpOnly": true,
      "secure": true,
      "sameSite": "Lax"
    },
    {
      "name": "__Secure-3PSID",
      "value": "g.a000vwhL4N3uIaXr_vZWHim6u55wOulT-VdaUqjxM1YX88tK2JJtsETTiiDxCZJl0Dw6_yAjrQACgYKAegSARESFQHGX2Mi5ysz_ajcbBPpdFrJNyHwExoVAUF8yKpwAIy5HI37xHPKRq5JigeP0076",
      "domain": ".google.com",
      "path": "/",
      "expires": 1778937017.511102,
      "httpOnly": true,
      "secure": true,
      "sameSite": "Lax"
    },
    {
      "name": "HSID",
      "value": "A9VpzH5jO_Ni_iz8M",
      "domain": ".google.com",
      "path": "/",
      "expires": 1778937017.511173,
      "httpOnly": true,
      "secure": false,
      "sameSite": "Lax"
    },
    {
      "name": "SSID",
      "value": "AmUkL1rLU2Ukp0-8n",
      "domain": ".google.com",
      "path": "/",
      "expires": 1778937017.511186,
      "httpOnly": true,
      "secure": true,
      "sameSite": "Lax"
    },
    {
      "name": "APISID",
      "value": "HKOtR4j_QwLXQBsr/AwNDh-22X2f0jHlrl",
      "domain": ".google.com",
      "path": "/",
      "expires": 1778937017.511199,
      "httpOnly": false,
      "secure": false,
      "sameSite": "Lax"
    },
    {
      "name": "SAPISID",
      "value": "mDk44C7JEwOgJvxw/AFb3_l_XO991vCWHo",
      "domain": ".google.com",
      "path": "/",
      "expires": 1778937017.511212,
      "httpOnly": false,
      "secure": true,
      "sameSite": "Lax"
    },
    {
      "name": "__Secure-1PAPISID",
      "value": "mDk44C7JEwOgJvxw/AFb3_l_XO991vCWHo",
      "domain": ".google.com",
      "path": "/",
      "expires": 1778937017.511225,
      "httpOnly": false,
      "secure": true,
      "sameSite": "Lax"
    },
    {
      "name": "__Secure-3PAPISID",
      "value": "mDk44C7JEwOgJvxw/AFb3_l_XO991vCWHo",
      "domain": ".google.com",
      "path": "/",
      "expires": 1778937017.511238,
      "httpOnly": false,
      "secure": true,
      "sameSite": "Lax"
    },
    {
      "name": "ACCOUNT_CHOOSER",
      "value": "AFx_qI5eI4jKHRKP-jqx4xeYWEzhOla96d28WmCiikLHgaKZTfRoUdTD_s4VPeXqf4Xy8bmEtNrCucLkHriX2CXX2-rv5BaHpA3dCRpZakJmw7Nd9XAqgt8",
      "domain": "accounts.google.com",
      "path": "/",
      "expires": 1778937017.511251,
      "httpOnly": true,
      "secure": true,
      "sameSite": "Lax"
    },
    {
      "name": "__Host-GAPS",
      "value": "1:kFQnsq1EO1t-hge21DPYevr1FFnmry_DdKcOu1RyifDYaeR7CRgKoVhS5C2wwmIrozhmmEULBmF8Jad2mJL4-qLJVgTliQ:BlWqJGkarekeobor",
      "domain": "accounts.google.com",
      "path": "/",
      "expires": 1778937017.511263,
      "httpOnly": true,
      "secure": true,
      "sameSite": "Lax"
    },
    {
      "name": "SMSV",
      "value": "ADHTe-D9jBOtdVrL4P5-1V6QURaBOpFaOSYHMZ6LGIpxHfJzVa2S2jTPGR9LAApHgaOKQTzVgNjsa6h_duH3itdEZu7KS5ToeQfP60ibEZFUQbBil-LFEKY",
      "domain": "accounts.google.com",
      "path": "/",
      "expires": 1778937017.511281,
      "httpOnly": true,
      "secure": true,
      "sameSite": "Lax"
    },
    {
      "name": "LSID",
      "value": "s.DE:g.a000vwhL4JnTY9UT_PvHhJslcK6WfrP6HWmYC4eRaFu155jh3ftXZfAhsfCzTVR6DJI7haBulwACgYKAW4SARESFQHGX2MijGlesI7CG9KXxcufO61kwhoVAUF8yKqsw4UqLvv4t9SP0vs_fblM0076",
      "domain": "accounts.google.com",
      "path": "/",
      "expires": 1778937017.636572,
      "httpOnly": true,
      "secure": true,
      "sameSite": "Lax"
    },
    {
      "name": "__Host-1PLSID",
      "value": "s.DE:g.a000vwhL4JnTY9UT_PvHhJslcK6WfrP6HWmYC4eRaFu155jh3ftXOSOQ3YfNBms3q5y-LNx94gACgYKAcoSARESFQHGX2Mij6w8KBYTFq3-qW5qARpznBoVAUF8yKoeZ4lrIzXEiLX_HUe5sL610076",
      "domain": "accounts.google.com",
      "path": "/",
      "expires": 1778937017.636683,
      "httpOnly": true,
      "secure": true,
      "sameSite": "Lax"
    },
    {
      "name": "__Host-3PLSID",
      "value": "s.DE:g.a000vwhL4JnTY9UT_PvHhJslcK6WfrP6HWmYC4eRaFu155jh3ftXr8y5vYlT9EDMTe4lGrDonAACgYKAfMSARESFQHGX2MiPN9ieTf6mNNqYWcwpnGqsxoVAUF8yKoTqDWbIUkV2ctvob2snxSB0076",
      "domain": "accounts.google.com",
      "path": "/",
      "expires": 1778937017.636732,
      "httpOnly": true,
      "secure": true,
      "sameSite": "Lax"
    },
    {
      "name": "HSID",
      "value": "AULgSfpimpSAoKeXU",
      "domain": ".google.de",
      "path": "/",
      "expires": 1778937017.734814,
      "httpOnly": true,
      "secure": false,
      "sameSite": "Lax"
    },
    {
      "name": "SSID",
      "value": "AHGYwWT6FljD5TxMk",
      "domain": ".google.de",
      "path": "/",
      "expires": 1778937017.734911,
      "httpOnly": true,
      "secure": true,
      "sameSite": "Lax"
    },
    {
      "name": "APISID",
      "value": "HKOtR4j_QwLXQBsr/AwNDh-22X2f0jHlrl",
      "domain": ".google.de",
      "path": "/",
      "expires": 1778937017.734948,
      "httpOnly": false,
      "secure": false,
      "sameSite": "Lax"
    },
    {
      "name": "SAPISID",
      "value": "mDk44C7JEwOgJvxw/AFb3_l_XO991vCWHo",
      "domain": ".google.de",
      "path": "/",
      "expires": 1778937017.734983,
      "httpOnly": false,
      "secure": true,
      "sameSite": "Lax"
    },
    {
      "name": "__Secure-1PAPISID",
      "value": "mDk44C7JEwOgJvxw/AFb3_l_XO991vCWHo",
      "domain": ".google.de",
      "path": "/",
      "expires": 1778937017.735018,
      "httpOnly": false,
      "secure": true,
      "sameSite": "Lax"
    },
    {
      "name": "__Secure-3PAPISID",
      "value": "mDk44C7JEwOgJvxw/AFb3_l_XO991vCWHo",
      "domain": ".google.de",
      "path": "/",
      "expires": 1778937017.735134,
      "httpOnly": false,
      "secure": true,
      "sameSite": "Lax"
    },
    {
      "name": "NID",
      "value": "523=frqNSAsgkjVDBPTrEqtzwWawHNUIMzB5zoawBAAI5HjdDyMiMPDXYadyz_bBDKV-Q4U01S6TSH0j4uFFB7VSlBZbgO8Knu9x0_hKOgklJsKHgsKLMaWO54waBWKgSAYcbace1Rpx6KGbnLB0ErNVN9LXJDh2KvR00sC__Utwd0Z3UGnamZ6tT_cvTgbe8NhDg4nq-CYrig",
      "domain": ".google.de",
      "path": "/",
      "expires": 1760188217.735185,
      "httpOnly": true,
      "secure": true,
      "sameSite": "Lax"
    },
    {
      "name": "SID",
      "value": "g.a000vwhL4N3uIaXr_vZWHim6u55wOulT-VdaUqjxM1YX88tK2JJt81RO2Ut6xhpYNcdAe_rw4wACgYKAaQSARESFQHGX2MiHf8vzqgzesHILBxz3k7mWxoVAUF8yKrS9GBzogQukA0U9LIXf0hL0076",
      "domain": ".google.de",
      "path": "/",
      "expires": 1778937017.735229,
      "httpOnly": false,
      "secure": false,
      "sameSite": "Lax"
    },
    {
      "name": "__Secure-1PSID",
      "value": "g.a000vwhL4N3uIaXr_vZWHim6u55wOulT-VdaUqjxM1YX88tK2JJtsLsDACqkvvs4EYnI9Q2S3AACgYKASgSARESFQHGX2Mi3mTF1WJbb-6jaVsJfq5QfRoVAUF8yKqIoUFFV7AI08eQyGheu4JR0076",
      "domain": ".google.de",
      "path": "/",
      "expires": 1778937017.735268,
      "httpOnly": true,
      "secure": true,
      "sameSite": "Lax"
    },
    {
      "name": "__Secure-3PSID",
      "value": "g.a000vwhL4N3uIaXr_vZWHim6u55wOulT-VdaUqjxM1YX88tK2JJtsETTiiDxCZJl0Dw6_yAjrQACgYKAegSARESFQHGX2Mi5ysz_ajcbBPpdFrJNyHwExoVAUF8yKpwAIy5HI37xHPKRq5JigeP0076",
      "domain": ".google.de",
      "path": "/",
      "expires": 1778937017.735309,
      "httpOnly": true,
      "secure": true,
      "sameSite": "Lax"
    },
    {
      "name": "__Secure-ENID",
      "value": "26.SE=KBFu-oz2YabzSBVcy-q2qK2s4d7ZdPiZbgijOArUIjOLtQYmyqA4wy9VeinbI1YSuWYo5ob_CQKbGWnJsSiOeg6Np9X0DVsVm2Dz9-eAQXmzeCeIn5sRvUE8DipV0v7picYNsR5AJVibFjzG-SQH41P9-4SDKF5s2kTYtunFQwMggO-c0GbcSoj_P5T8p8_gmsRaoj5o",
      "domain": ".google.com",
      "path": "/",
      "expires": 1778563715.813627,
      "httpOnly": true,
      "secure": true,
      "sameSite": "Lax"
    },
    {
      "name": "SIDCC",
      "value": "AKEyXzU_VhN8gzs3QT8BYOC0QDAQ5pbvk_hIQ3FUprnJevWvoGXBx_gluE2kIinjmfMA_xsgKA",
      "domain": ".google.com",
      "path": "/",
      "expires": 1775913018.020684,
      "httpOnly": false,
      "secure": false,
      "sameSite": "Lax"
    },
    {
      "name": "__Secure-1PSIDCC",
      "value": "AKEyXzVuXhPLi-VGpsMCuE7QTost8lUKX3BGNjE5q6kMC4EzxgLfn1DAVsiO3gl5HilJ-F7Z",
      "domain": ".google.com",
      "path": "/",
      "expires": 1775913018.020786,
      "httpOnly": true,
      "secure": true,
      "sameSite": "Lax"
    },
    {
      "name": "__Secure-3PSIDCC",
      "value": "AKEyXzXvoJfxas8L9PrOGpK7o3G7afc39D-43zyIMN65RSbxRBK3xDNbe1kWf_pbeQYlzrur_g",
      "domain": ".google.com",
      "path": "/",
      "expires": 1775913018.02083,
      "httpOnly": true,
      "secure": true,
      "sameSite": "Lax"
    },
    {
      "name": "_faircare_session",
      "value": "NHZocHlRT0RndElGcllLejNMbTVWNnJEb29SV0dvY0VkekZZT1JjRDMyZjFxVXZJSTUvcUpWdzJXdjhGZWRoVmE2bC9QNUZmOTlpcVh0ZmtUdzdteGp0NnFLQzV0bmhYK3ZPSnExM3YrbkNGcThuYlZyMUJmZEt6TzFzUXZKUHFGbC9HS2dRTXhYZ09QNlZQUG5ncE1wRGdBekJiSDlwWnpyUjQrbHQ1OG1ZPS0tTUUyY3JsNzQ2c2dHcmhTdnJ5bTNGUT09--1bfe4d09696e1f0954fc525ba7c564db356d4bca",
      "domain": "beta7.dentolo-test.de",
      "path": "/",
      "expires": -1,
      "httpOnly": true,
      "secure": false,
      "sameSite": "Lax"
    }
  ],
  "origins": []
}